petrel/__init__.py
petrel/cmdline.py
petrel/emitter.py
petrel/mock.py
petrel/package.py
petrel/rdebug.py
petrel/run.py
petrel/status.py
petrel/storm.py
petrel/topologybuilder.py
petrel/util.py
petrel/generated/__init__.py
petrel/generated/storm-petrel-1.0.2-SNAPSHOT-jar-with-dependencies.jar
petrel/generated/storm-petrel-1.0.3-SNAPSHOT-jar-with-dependencies.jar
petrel/generated/storm/DistributedRPC.py
petrel/generated/storm/DistributedRPCInvocations.py
petrel/generated/storm/Nimbus.py
petrel/generated/storm/__init__.py
petrel/generated/storm/constants.py
petrel/generated/storm/ttypes.py
petrel/tests/__init__.py
petrel/tests/test_topology.py
petrel-1.0.3.0.3.post1.data/scripts/petrel
petrel-1.0.3.0.3.post1.dist-info/DESCRIPTION.rst
petrel-1.0.3.0.3.post1.dist-info/METADATA
petrel-1.0.3.0.3.post1.dist-info/RECORD
petrel-1.0.3.0.3.post1.dist-info/WHEEL
petrel-1.0.3.0.3.post1.dist-info/metadata.json
petrel-1.0.3.0.3.post1.dist-info/top_level.txt
