Metadata-Version: 2.0
Name: petrel
Version: 1.0.3.0.3.post1
Summary: Storm Topology Builder
Home-page: https://github.com/AirSage/Petrel
Author: bhart
Author-email: UNKNOWN
License: BSD 3-clause
Keywords: Storm Topology Builder
Platform: UNKNOWN
Classifier: Programming Language :: Python
Classifier: Operating System :: POSIX :: Linux
Classifier: Development Status :: 5 - Production/Stable
Classifier: Intended Audience :: Developers
Classifier: License :: OSI Approved :: BSD License
Classifier: Topic :: Software Development :: Libraries :: Python Modules
Classifier: Topic :: System :: Distributed Computing
Requires-Dist: PyYAML (==3.10)
Requires-Dist: six (==1.10.0)
Requires-Dist: thrift (==0.9.3)
